{"name":"swiss_knife","latest":{"version":"3.2.2","pubspec":{"name":"swiss_knife","description":"Dart Useful Tools - collections, math, date, uri, json, events, resources, regexp, etc...","version":"3.2.2","homepage":"https://github.com/gmpassos/swiss_knife","environment":{"sdk":">=3.3.0 <4.0.0"},"dependencies":{"intl":"^0.19.0","resource_portable":"^3.1.0"},"dev_dependencies":{"lints":"^3.0.0","test":"^1.25.8","dependency_validator":"^3.2.3","collection":"^1.18.0","coverage":"^1.9.2"}},"archive_url":"https://pub.dev/api/archives/swiss_knife-3.2.2.tar.gz","archive_sha256":"c0b011aab38df274c08f90ce42549aa66d744115c011e07a9bd21402d6be297d","published":"2024-09-14T08:01:15.749783Z"},"versions":[{"version":"1.0.0","pubspec":{"version":"1.0.0","name":"swiss_knife","dependencies":{"intl":"^0.15.7"},"author":"gmpassos <gracilianomp@gmail.com>","description":"Dart useful tools, collections, math, date, etc...","homepage":"https://github.com/gmpassos/swiss_knife","environment":{"sdk":">=2.0.0 <3.0.0"},"dev_dependencies":{"test":"^1.0.0"}},"archive_url":"https://pub.dev/api/archives/swiss_knife-1.0.0.tar.gz","archive_sha256":"38eb1ee58bca4519949776d8b526dce7d9da6b2f5d73b536656110868c40cfbb","published":"2018-09-25T21:10:39.524781Z"},{"version":"1.0.1","pubspec":{"version":"1.0.1","name":"swiss_knife","dependencies":{"intl":"^0.15.7"},"author":"gmpassos <gracilianomp@gmail.com>","description":"Dart useful tools, collections, math, date, etc...","homepage":"https://github.com/gmpassos/swiss_knife","environment":{"sdk":">=2.0.0 <3.0.0"},"dev_dependencies":{"test":"^1.0.1"}},"archive_url":"https://pub.dev/api/archives/swiss_knife-1.0.1.tar.gz","archive_sha256":"9e9499c0f7377c6b4a4ba79d46e350b21137c03989f503be0628636d6d89071f","published":"2018-09-25T21:34:31.919048Z"},{"version":"2.0.0","pubspec":{"version":"2.0.0","name":"swiss_knife","dependencies":{"intl":"^0.15.7"},"author":"gmpassos <gracilianomp@gmail.com>","description":"Dart useful tools, collections, math, date, etc...","homepage":"https://github.com/gmpassos/swiss_knife","environment":{"sdk":">=2.0.1 <3.0.0"},"dev_dependencies":{"test":"^1.5.1"}},"archive_url":"https://pub.dev/api/archives/swiss_knife-2.0.0.tar.gz","archive_sha256":"6b6240b3fa8cd14c3c79d6f61743d55bf4c9a89ac6d5a15085f0791f4f889d64","published":"2019-01-06T19:05:39.466068Z"},{"version":"2.1.0","pubspec":{"version":"2.1.0","name":"swiss_knife","dependencies":{"intl":"^0.15.7"},"author":"gmpassos <gracilianomp@gmail.com>","description":"Dart useful tools, collections, math, date, etc...","homepage":"https://github.com/gmpassos/swiss_knife","environment":{"sdk":">=2.0.1 <3.0.0"},"dev_dependencies":{"test":"^1.5.1"}},"archive_url":"https://pub.dev/api/archives/swiss_knife-2.1.0.tar.gz","archive_sha256":"256e1d6e1c8adf7b24f93a451ac0906b055af4327e07b54c1bcdcddf70a480da","published":"2019-08-16T17:24:48.638025Z"},{"version":"2.1.1","pubspec":{"version":"2.1.1","name":"swiss_knife","dependencies":{"intl":"^0.15.7"},"author":"gmpassos <gracilianomp@gmail.com>","description":"Dart useful tools, collections, math, date, etc...","homepage":"https://github.com/gmpassos/swiss_knife","environment":{"sdk":">=2.0.1 <3.0.0"},"dev_dependencies":{"test":"^1.5.1"}},"archive_url":"https://pub.dev/api/archives/swiss_knife-2.1.1.tar.gz","archive_sha256":"ad685d2848c82760c5bfe2567d708b364c19345c195c5dcd4c6dc7fffaca8146","published":"2019-08-16T17:29:00.014892Z"},{"version":"2.1.2","pubspec":{"version":"2.1.2","name":"swiss_knife","dependencies":{"intl":"^0.15.7"},"author":"gmpassos <gracilianomp@gmail.com>","description":"Dart useful tools, collections, math, date, etc...","homepage":"https://github.com/gmpassos/swiss_knife","environment":{"sdk":">=2.0.1 <3.0.0"},"dev_dependencies":{"test":"^1.5.1"}},"archive_url":"https://pub.dev/api/archives/swiss_knife-2.1.2.tar.gz","archive_sha256":"38ca7f113d0427122de86350599c462004ba7812968c5d931b3dc2503384a6c9","published":"2019-10-11T16:30:00.454431Z"},{"version":"2.2.0","pubspec":{"name":"swiss_knife","description":"Dart useful tools, collections, math, date, etc...","version":"2.2.0","homepage":"https://github.com/gmpassos/swiss_knife","environment":{"sdk":">=2.2.0 <3.0.0"},"dependencies":{"intl":"^0.15.7","enum_to_string":"^1.0.7"},"dev_dependencies":{"test":"^1.5.1"}},"archive_url":"https://pub.dev/api/archives/swiss_knife-2.2.0.tar.gz","archive_sha256":"cfa5593571c122baf9939c70c6b26e3381403cd4f0947cabbf5bd9e986fb782d","published":"2020-01-07T00:14:51.388224Z"},{"version":"2.2.1","pubspec":{"name":"swiss_knife","description":"Dart useful tools, collections, math, date, etc...","version":"2.2.1","homepage":"https://github.com/gmpassos/swiss_knife","environment":{"sdk":">=2.2.0 <3.0.0"},"dependencies":{"intl":"^0.16.1"},"dev_dependencies":{"test":"^1.5.1"}},"archive_url":"https://pub.dev/api/archives/swiss_knife-2.2.1.tar.gz","archive_sha256":"0d03cfe2365c0010211d93cc352bc4ccfcf7156d6d3715bb55aa00b49b98c777","published":"2020-01-08T03:19:03.717432Z"},{"version":"2.3.0","pubspec":{"name":"swiss_knife","description":"Dart useful tools, collections, math, date, etc...","version":"2.3.0","homepage":"https://github.com/gmpassos/swiss_knife","environment":{"sdk":">=2.2.0 <3.0.0"},"dependencies":{"intl":"^0.16.1"},"dev_dependencies":{"test":"^1.5.1"}},"archive_url":"https://pub.dev/api/archives/swiss_knife-2.3.0.tar.gz","archive_sha256":"a6c9cbe863a51c8383c208dac95cc2853a274b7399c560166ba6784e5e6ed8bd","published":"2020-03-06T05:45:02.379454Z"},{"version":"2.3.1","pubspec":{"name":"swiss_knife","description":"Dart useful tools, collections, math, date, etc...","version":"2.3.1","homepage":"https://github.com/gmpassos/swiss_knife","environment":{"sdk":">=2.6.0 <3.0.0"},"dependencies":{"intl":"^0.16.1"},"dev_dependencies":{"test":"^1.5.1"}},"archive_url":"https://pub.dev/api/archives/swiss_knife-2.3.1.tar.gz","archive_sha256":"ac42568bb1315f1c8a846702ca66f83d57fcf82d623a54fc51f4ed34db1dd4c8","published":"2020-03-06T06:02:21.718112Z"},{"version":"2.3.2","pubspec":{"name":"swiss_knife","description":"Dart useful tools, collections, math, date, etc...","version":"2.3.2","homepage":"https://github.com/gmpassos/swiss_knife","environment":{"sdk":">=2.6.0 <3.0.0"},"dependencies":{"intl":"^0.16.1"},"dev_dependencies":{"test":"^1.5.1"}},"archive_url":"https://pub.dev/api/archives/swiss_knife-2.3.2.tar.gz","archive_sha256":"6918f605d8a577e104abe0c17fe60274ca6b6519201aa00307230b4198809b6f","published":"2020-03-12T19:19:50.322246Z"},{"version":"2.3.3","pubspec":{"name":"swiss_knife","description":"Dart useful tools, collections, math, date, etc...","version":"2.3.3","homepage":"https://github.com/gmpassos/swiss_knife","environment":{"sdk":">=2.6.0 <3.0.0"},"dependencies":{"intl":"^0.16.1"},"dev_dependencies":{"test":"^1.5.1"}},"archive_url":"https://pub.dev/api/archives/swiss_knife-2.3.3.tar.gz","archive_sha256":"bcf89ac287411d11b7fc4f2d4fb9f61291b41bafbfc9632c8d02a43cc69262da","published":"2020-03-12T20:13:27.091556Z"},{"version":"2.3.4","pubspec":{"name":"swiss_knife","description":"Dart useful tools, collections, math, date, etc...","version":"2.3.4","homepage":"https://github.com/gmpassos/swiss_knife","environment":{"sdk":">=2.6.0 <3.0.0"},"dependencies":{"intl":"^0.16.1"},"dev_dependencies":{"test":"^1.5.1"}},"archive_url":"https://pub.dev/api/archives/swiss_knife-2.3.4.tar.gz","archive_sha256":"ef46df62334e1e605c6004699112dfcd25462d1c481d6d847c46f3f19de5143e","published":"2020-03-12T21:22:19.340978Z"},{"version":"2.3.5","pubspec":{"name":"swiss_knife","description":"Dart useful tools, collections, math, date, etc...","version":"2.3.5","homepage":"https://github.com/gmpassos/swiss_knife","environment":{"sdk":">=2.6.0 <3.0.0"},"dependencies":{"intl":"^0.16.1"},"dev_dependencies":{"test":"^1.5.1"}},"archive_url":"https://pub.dev/api/archives/swiss_knife-2.3.5.tar.gz","archive_sha256":"52e36e46aaf29182aaf1506e1e203b64381c708968391176d15a271552e8cc89","published":"2020-03-13T04:52:21.285694Z"},{"version":"2.3.6","pubspec":{"name":"swiss_knife","description":"Dart useful tools, collections, math, date, etc...","version":"2.3.6","homepage":"https://github.com/gmpassos/swiss_knife","environment":{"sdk":">=2.6.0 <3.0.0"},"dependencies":{"intl":"^0.16.1"},"dev_dependencies":{"test":"^1.5.1"}},"archive_url":"https://pub.dev/api/archives/swiss_knife-2.3.6.tar.gz","archive_sha256":"97b8a252cbd615fa1ef650af0dcdd3dacc7b59e1ed493eec8fc086bea65fb603","published":"2020-03-13T22:34:29.827024Z"},{"version":"2.3.7","pubspec":{"name":"swiss_knife","description":"Dart useful tools, collections, math, date, etc...","version":"2.3.7","homepage":"https://github.com/gmpassos/swiss_knife","environment":{"sdk":">=2.6.0 <3.0.0"},"dependencies":{"intl":"^0.16.1"},"dev_dependencies":{"test":"^1.5.1"}},"archive_url":"https://pub.dev/api/archives/swiss_knife-2.3.7.tar.gz","archive_sha256":"9b9c03f49e1b3ef2fa35ef36097f9c79218d9ee79f2f4955c02baf8321b78a06","published":"2020-03-16T00:03:35.985827Z"},{"version":"2.3.8","pubspec":{"name":"swiss_knife","description":"Dart useful tools, collections, math, date, etc...","version":"2.3.8","homepage":"https://github.com/gmpassos/swiss_knife","environment":{"sdk":">=2.6.0 <3.0.0"},"dependencies":{"intl":"^0.16.1"},"dev_dependencies":{"test":"^1.5.1"}},"archive_url":"https://pub.dev/api/archives/swiss_knife-2.3.8.tar.gz","archive_sha256":"5079919fe6e37759bf09927fc59b30ab0be4f8b7bea4d36217639fe251dae64f","published":"2020-03-17T06:31:48.803955Z"},{"version":"2.3.9","pubspec":{"name":"swiss_knife","description":"Dart useful tools, collections, math, date, etc...","version":"2.3.9","homepage":"https://github.com/gmpassos/swiss_knife","environment":{"sdk":">=2.6.0 <3.0.0"},"dependencies":{"intl":"^0.16.1","resource_portable":"^2.1.7"},"dev_dependencies":{"test":"^1.5.1"}},"archive_url":"https://pub.dev/api/archives/swiss_knife-2.3.9.tar.gz","archive_sha256":"4d54bcf94d2f7868b5e0015336548d66427ad46bd4a9c6d537ca7e246c41a722","published":"2020-03-24T11:09:00.265825Z"},{"version":"2.3.10","pubspec":{"name":"swiss_knife","description":"Dart useful tools, collections, math, date, etc...","version":"2.3.10","homepage":"https://github.com/gmpassos/swiss_knife","environment":{"sdk":">=2.6.0 <3.0.0"},"dependencies":{"intl":"^0.16.1","resource_portable":"^2.1.7"},"dev_dependencies":{"test":"^1.5.1"}},"archive_url":"https://pub.dev/api/archives/swiss_knife-2.3.10.tar.gz","archive_sha256":"d5790ceb75f622b10b785cfd3ec0c497d07969acc16fdd1d5507bf7e53f18b11","published":"2020-04-18T16:02:12.379555Z"},{"version":"2.4.0","pubspec":{"name":"swiss_knife","description":"Dart Useful Tools - collections, math, date, uri, json, events, resources, etc...","version":"2.4.0","homepage":"https://github.com/gmpassos/swiss_knife","environment":{"sdk":">=2.6.0 <3.0.0"},"dependencies":{"intl":"^0.16.1","resource_portable":"^2.1.7"},"dev_dependencies":{"test":"^1.5.1"}},"archive_url":"https://pub.dev/api/archives/swiss_knife-2.4.0.tar.gz","archive_sha256":"26ba5668f0a76d5cfeb72af4d0085d72ec7f59fab58750bad3d9677ecc27a14a","published":"2020-05-21T06:40:56.331307Z"},{"version":"2.4.1","pubspec":{"name":"swiss_knife","description":"Dart Useful Tools - collections, math, date, uri, json, events, resources, etc...","version":"2.4.1","homepage":"https://github.com/gmpassos/swiss_knife","environment":{"sdk":">=2.6.0 <3.0.0"},"dependencies":{"intl":"^0.16.1","resource_portable":"^2.1.7"},"dev_dependencies":{"test":"^1.14.4"}},"archive_url":"https://pub.dev/api/archives/swiss_knife-2.4.1.tar.gz","archive_sha256":"73780228225df8499a24008f344883a9489d5f266f843ec1d20ff27c4f8dec31","published":"2020-05-29T04:09:48.126886Z"},{"version":"2.4.2","pubspec":{"name":"swiss_knife","description":"Dart Useful Tools - collections, math, date, uri, json, events, resources, etc...","version":"2.4.2","homepage":"https://github.com/gmpassos/swiss_knife","environment":{"sdk":">=2.6.0 <3.0.0"},"dependencies":{"intl":"^0.16.1","resource_portable":"^2.1.7"},"dev_dependencies":{"test":"^1.14.4"}},"archive_url":"https://pub.dev/api/archives/swiss_knife-2.4.2.tar.gz","archive_sha256":"fe55ba89d0923835af78ac0c917cee711338777e3c02f29039a64b1f5b8a8db6","published":"2020-05-31T06:35:51.530576Z"},{"version":"2.5.0","pubspec":{"name":"swiss_knife","description":"Dart Useful Tools - collections, math, date, uri, json, events, resources, regexp, etc...","version":"2.5.0","homepage":"https://github.com/gmpassos/swiss_knife","environment":{"sdk":">=2.6.0 <3.0.0"},"dependencies":{"intl":"^0.16.1","resource_portable":"^2.1.7"},"dev_dependencies":{"test":"^1.14.4"}},"archive_url":"https://pub.dev/api/archives/swiss_knife-2.5.0.tar.gz","archive_sha256":"8628903900c0bf14eba33549f9ed8ebcd0d9522b7bfac10653539807357e63aa","published":"2020-05-31T06:44:48.954866Z"},{"version":"2.5.1","pubspec":{"name":"swiss_knife","description":"Dart Useful Tools - collections, math, date, uri, json, events, resources, regexp, etc...","version":"2.5.1","homepage":"https://github.com/gmpassos/swiss_knife","environment":{"sdk":">=2.6.0 <3.0.0"},"dependencies":{"intl":"^0.16.1","resource_portable":"^2.1.7"},"dev_dependencies":{"test":"^1.14.4"}},"archive_url":"https://pub.dev/api/archives/swiss_knife-2.5.1.tar.gz","archive_sha256":"f2ad9d44514546f8220ff017f47f1864c6fda6a4bac160bf1990eb9afb241374","published":"2020-06-03T03:01:05.245129Z"},{"version":"2.5.2","pubspec":{"name":"swiss_knife","description":"Dart Useful Tools - collections, math, date, uri, json, events, resources, regexp, etc...","version":"2.5.2","homepage":"https://github.com/gmpassos/swiss_knife","environment":{"sdk":">=2.6.0 <3.0.0"},"dependencies":{"intl":"^0.16.1","resource_portable":"^2.1.7"},"dev_dependencies":{"test":"^1.14.4"}},"archive_url":"https://pub.dev/api/archives/swiss_knife-2.5.2.tar.gz","archive_sha256":"ae3b008c9ea3296494b2ee14510da0271bd52722810817e8f205767be5ac5251","published":"2020-06-03T04:41:59.407432Z"},{"version":"2.5.3","pubspec":{"name":"swiss_knife","description":"Dart Useful Tools - collections, math, date, uri, json, events, resources, regexp, etc...","version":"2.5.3","homepage":"https://github.com/gmpassos/swiss_knife","environment":{"sdk":">=2.6.0 <3.0.0"},"dependencies":{"intl":"^0.16.1","resource_portable":"^2.1.7"},"dev_dependencies":{"test":"^1.14.4"}},"archive_url":"https://pub.dev/api/archives/swiss_knife-2.5.3.tar.gz","archive_sha256":"e7d22b4cd31472f44e9003cf9795d68c7d9fb7853718c6a51151b0e72ef274ad","published":"2020-06-12T06:36:16.328761Z"},{"version":"2.5.4","pubspec":{"name":"swiss_knife","description":"Dart Useful Tools - collections, math, date, uri, json, events, resources, regexp, etc...","version":"2.5.4","homepage":"https://github.com/gmpassos/swiss_knife","environment":{"sdk":">=2.6.0 <3.0.0"},"dependencies":{"intl":"^0.16.1","resource_portable":"^2.1.7"},"dev_dependencies":{"test":"^1.14.4"}},"archive_url":"https://pub.dev/api/archives/swiss_knife-2.5.4.tar.gz","archive_sha256":"025c62c4db2e5b7f2cd65437f81bf674357a3436222165dc3ea7a1e8a3eb1cf3","published":"2020-07-11T08:02:00.420585Z"},{"version":"2.5.5","pubspec":{"name":"swiss_knife","description":"Dart Useful Tools - collections, math, date, uri, json, events, resources, regexp, etc...","version":"2.5.5","homepage":"https://github.com/gmpassos/swiss_knife","environment":{"sdk":">=2.6.0 <3.0.0"},"dependencies":{"intl":"^0.16.1","resource_portable":"^2.1.7"},"dev_dependencies":{"test":"^1.14.4"}},"archive_url":"https://pub.dev/api/archives/swiss_knife-2.5.5.tar.gz","archive_sha256":"ae1aa5547e8f25bc9c0ad3a37e7e8e6b3c5c9e992d044190cc57499844f7d691","published":"2020-07-13T16:59:02.424836Z"},{"version":"2.5.6","pubspec":{"name":"swiss_knife","description":"Dart Useful Tools - collections, math, date, uri, json, events, resources, regexp, etc...","version":"2.5.6","homepage":"https://github.com/gmpassos/swiss_knife","environment":{"sdk":">=2.6.0 <3.0.0"},"dependencies":{"intl":"^0.16.1","resource_portable":"^2.1.7"},"dev_dependencies":{"test":"^1.14.4","test_coverage":"^0.4.2"}},"archive_url":"https://pub.dev/api/archives/swiss_knife-2.5.6.tar.gz","archive_sha256":"3f526de1f84074424b9d33f9dfcc8b2135e7d4cfadebc917f76c79e2c9689413","published":"2020-07-17T00:54:04.112779Z"},{"version":"2.5.7","pubspec":{"name":"swiss_knife","description":"Dart Useful Tools - collections, math, date, uri, json, events, resources, regexp, etc...","version":"2.5.7","homepage":"https://github.com/gmpassos/swiss_knife","environment":{"sdk":">=2.6.0 <3.0.0"},"dependencies":{"intl":"^0.16.1","resource_portable":"^2.1.7"},"dev_dependencies":{"test":"^1.14.4","test_coverage":"^0.4.2"}},"archive_url":"https://pub.dev/api/archives/swiss_knife-2.5.7.tar.gz","archive_sha256":"60c75bbf04055bbffeee8ca17d105e7082fb1227b398f1764671a1e865ad5a81","published":"2020-07-18T06:23:06.463026Z"},{"version":"2.5.8","pubspec":{"name":"swiss_knife","description":"Dart Useful Tools - collections, math, date, uri, json, events, resources, regexp, etc...","version":"2.5.8","homepage":"https://github.com/gmpassos/swiss_knife","environment":{"sdk":">=2.6.0 <3.0.0"},"dependencies":{"intl":"^0.16.1","resource_portable":"^2.1.7"},"dev_dependencies":{"test":"^1.14.4","test_coverage":"^0.4.2"}},"archive_url":"https://pub.dev/api/archives/swiss_knife-2.5.8.tar.gz","archive_sha256":"b2a34991d52cf2d9cc113ed7cca98be8cee88b2692281de05747c4bd516d4737","published":"2020-08-02T07:08:22.018373Z"},{"version":"2.5.9","pubspec":{"name":"swiss_knife","description":"Dart Useful Tools - collections, math, date, uri, json, events, resources, regexp, etc...","version":"2.5.9","homepage":"https://github.com/gmpassos/swiss_knife","environment":{"sdk":">=2.6.0 <3.0.0"},"dependencies":{"intl":"^0.16.1","resource_portable":"^2.1.7"},"dev_dependencies":{"test":"^1.14.4","test_coverage":"^0.4.2"}},"archive_url":"https://pub.dev/api/archives/swiss_knife-2.5.9.tar.gz","archive_sha256":"8db4681c6701fcdf5063c1237161cb537848d4238d60c6223c25fc7c75a9dc0a","published":"2020-08-16T06:12:59.806383Z"},{"version":"2.5.10","pubspec":{"name":"swiss_knife","description":"Dart Useful Tools - collections, math, date, uri, json, events, resources, regexp, etc...","version":"2.5.10","homepage":"https://github.com/gmpassos/swiss_knife","environment":{"sdk":">=2.6.0 <3.0.0"},"dependencies":{"intl":"^0.16.1","resource_portable":"^2.1.7"},"dev_dependencies":{"test":"^1.14.4","test_coverage":"^0.4.2"}},"archive_url":"https://pub.dev/api/archives/swiss_knife-2.5.10.tar.gz","archive_sha256":"dd5e24a3c5cf233b37b2e91007758c105e46515a4eb2be50d23c54cdc196b8ec","published":"2020-08-16T07:16:50.833907Z"},{"version":"2.5.11","pubspec":{"name":"swiss_knife","description":"Dart Useful Tools - collections, math, date, uri, json, events, resources, regexp, etc...","version":"2.5.11","homepage":"https://github.com/gmpassos/swiss_knife","environment":{"sdk":">=2.6.0 <3.0.0"},"dependencies":{"intl":"^0.16.1","resource_portable":"^2.1.7"},"dev_dependencies":{"test":"^1.14.4","test_coverage":"^0.4.2"}},"archive_url":"https://pub.dev/api/archives/swiss_knife-2.5.11.tar.gz","archive_sha256":"da19b1a350b578c5a88e39ee30a2fc6b15fa5670c8f6f5c34f1cda7d3f371c81","published":"2020-08-17T04:59:20.753407Z"},{"version":"2.5.12","pubspec":{"name":"swiss_knife","description":"Dart Useful Tools - collections, math, date, uri, json, events, resources, regexp, etc...","version":"2.5.12","homepage":"https://github.com/gmpassos/swiss_knife","environment":{"sdk":">=2.6.0 <3.0.0"},"dependencies":{"intl":"^0.16.1","resource_portable":"^2.1.7"},"dev_dependencies":{"test":"^1.14.4","test_coverage":"^0.4.2"}},"archive_url":"https://pub.dev/api/archives/swiss_knife-2.5.12.tar.gz","archive_sha256":"4e4a0a6fdef795edda93dd8090ded0a04822602e5123b3388fb5c0e65756d330","published":"2020-09-03T09:25:13.087276Z"},{"version":"2.5.13","pubspec":{"name":"swiss_knife","description":"Dart Useful Tools - collections, math, date, uri, json, events, resources, regexp, etc...","version":"2.5.13","homepage":"https://github.com/gmpassos/swiss_knife","environment":{"sdk":">=2.6.0 <3.0.0"},"dependencies":{"intl":"^0.16.1","resource_portable":"^2.1.7"},"dev_dependencies":{"test":"^1.14.4","test_coverage":"^0.4.2"}},"archive_url":"https://pub.dev/api/archives/swiss_knife-2.5.13.tar.gz","archive_sha256":"15d084edc28d305b0e381c0bc07f11b55a6c6bdd67f2a4030dc37de04dfdf778","published":"2020-09-04T10:59:31.928306Z"},{"version":"2.5.14","pubspec":{"name":"swiss_knife","description":"Dart Useful Tools - collections, math, date, uri, json, events, resources, regexp, etc...","version":"2.5.14","homepage":"https://github.com/gmpassos/swiss_knife","environment":{"sdk":">=2.6.0 <3.0.0"},"dependencies":{"intl":"^0.16.1","resource_portable":"^2.1.8"},"dev_dependencies":{"pedantic":"^1.9.2","test":"^1.15.4","test_coverage":"^0.4.3"}},"archive_url":"https://pub.dev/api/archives/swiss_knife-2.5.14.tar.gz","archive_sha256":"9df95ead9e8a1ca41c6d354929891f2b553a6b7d5c165c591ef89eec54fe715f","published":"2020-09-18T10:40:56.272321Z"},{"version":"2.5.15","pubspec":{"name":"swiss_knife","description":"Dart Useful Tools - collections, math, date, uri, json, events, resources, regexp, etc...","version":"2.5.15","homepage":"https://github.com/gmpassos/swiss_knife","environment":{"sdk":">=2.6.0 <3.0.0"},"dependencies":{"intl":"^0.16.1","resource_portable":"^2.1.8"},"dev_dependencies":{"pedantic":"^1.9.2","test":"^1.15.4","test_coverage":"^0.4.3"}},"archive_url":"https://pub.dev/api/archives/swiss_knife-2.5.15.tar.gz","archive_sha256":"f1affde5df4a28cfd5603c23b32842196e05f79a4dc3ca81d35a1ba19b79e2d5","published":"2020-10-08T23:35:17.086590Z"},{"version":"2.5.16","pubspec":{"name":"swiss_knife","description":"Dart Useful Tools - collections, math, date, uri, json, events, resources, regexp, etc...","version":"2.5.16","homepage":"https://github.com/gmpassos/swiss_knife","environment":{"sdk":">=2.6.0 <3.0.0"},"dependencies":{"intl":"^0.16.1","resource_portable":"^2.1.8"},"dev_dependencies":{"pedantic":"^1.9.2","test":"^1.15.4","test_coverage":"^0.4.3"}},"archive_url":"https://pub.dev/api/archives/swiss_knife-2.5.16.tar.gz","archive_sha256":"3c98ea584d56f6bdc2f79c2aeca1a23c9c872e47c7041dd451d68dccacf26f4d","published":"2020-10-25T08:28:55.897103Z"},{"version":"2.5.17","pubspec":{"name":"swiss_knife","description":"Dart Useful Tools - collections, math, date, uri, json, events, resources, regexp, etc...","version":"2.5.17","homepage":"https://github.com/gmpassos/swiss_knife","environment":{"sdk":">=2.6.0 <3.0.0"},"dependencies":{"intl":"^0.16.1","resource_portable":"^2.1.8"},"dev_dependencies":{"pedantic":"^1.9.2","test":"^1.15.4","test_coverage":"^0.4.3"}},"archive_url":"https://pub.dev/api/archives/swiss_knife-2.5.17.tar.gz","archive_sha256":"fa56775d8851a37b0665873ebfe3c9f005acd9539f3a9435de635ce9600c8c17","published":"2020-11-23T01:52:27.209176Z"},{"version":"2.5.18","pubspec":{"name":"swiss_knife","description":"Dart Useful Tools - collections, math, date, uri, json, events, resources, regexp, etc...","version":"2.5.18","homepage":"https://github.com/gmpassos/swiss_knife","environment":{"sdk":">=2.6.0 <3.0.0"},"dependencies":{"intl":"^0.16.1","resource_portable":"^2.1.8"},"dev_dependencies":{"pedantic":"^1.9.2","test":"^1.15.4","test_coverage":"^0.4.3"}},"archive_url":"https://pub.dev/api/archives/swiss_knife-2.5.18.tar.gz","archive_sha256":"dab66f76c455a328978b731fda09426c19fde6e375d8e1e4eb21bbf3451749de","published":"2020-11-23T02:07:51.330486Z"},{"version":"2.5.19","pubspec":{"name":"swiss_knife","description":"Dart Useful Tools - collections, math, date, uri, json, events, resources, regexp, etc...","version":"2.5.19","homepage":"https://github.com/gmpassos/swiss_knife","environment":{"sdk":">=2.6.0 <3.0.0"},"dependencies":{"intl":"^0.16.1","resource_portable":"^2.1.8"},"dev_dependencies":{"pedantic":"^1.9.2","test":"^1.15.4","test_coverage":"^0.4.3"}},"archive_url":"https://pub.dev/api/archives/swiss_knife-2.5.19.tar.gz","archive_sha256":"8060c744e46308ed2de77c27d5d43438602f032107b96140e5b33642f1a3cbc7","published":"2020-12-09T04:58:41.917375Z"},{"version":"2.5.20","pubspec":{"name":"swiss_knife","description":"Dart Useful Tools - collections, math, date, uri, json, events, resources, regexp, etc...","version":"2.5.20","homepage":"https://github.com/gmpassos/swiss_knife","environment":{"sdk":">=2.6.0 <3.0.0"},"dependencies":{"intl":"^0.16.1","resource_portable":"^2.1.8"},"dev_dependencies":{"pedantic":"^1.9.2","test":"^1.15.4","test_coverage":"^0.4.3"}},"archive_url":"https://pub.dev/api/archives/swiss_knife-2.5.20.tar.gz","archive_sha256":"d9c8e7761282b372d03d24cfb76cef7d06acaa77c0ef7e6b62d25e6fab11b00a","published":"2021-01-07T06:03:21.677769Z"},{"version":"2.5.21","pubspec":{"name":"swiss_knife","description":"Dart Useful Tools - collections, math, date, uri, json, events, resources, regexp, etc...","version":"2.5.21","homepage":"https://github.com/gmpassos/swiss_knife","environment":{"sdk":">=2.6.0 <3.0.0"},"dependencies":{"intl":"^0.16.1","resource_portable":"^2.1.8"},"dev_dependencies":{"pedantic":"^1.9.2","test":"^1.15.4","test_coverage":"^0.4.3"}},"archive_url":"https://pub.dev/api/archives/swiss_knife-2.5.21.tar.gz","archive_sha256":"46b3aef759ca2a9be4a33709c2e4cded6f081f30c768570741a7f61bde7b7cbc","published":"2021-01-17T09:42:27.719752Z"},{"version":"2.5.22","pubspec":{"name":"swiss_knife","description":"Dart Useful Tools - collections, math, date, uri, json, events, resources, regexp, etc...","version":"2.5.22","homepage":"https://github.com/gmpassos/swiss_knife","environment":{"sdk":">=2.6.0 <3.0.0"},"dependencies":{"intl":"^0.16.1","resource_portable":"^2.1.8"},"dev_dependencies":{"pedantic":"^1.9.2","test":"^1.15.4","test_coverage":"^0.4.3"}},"archive_url":"https://pub.dev/api/archives/swiss_knife-2.5.22.tar.gz","archive_sha256":"02034c22c08b2c868471b401965e690f89493714b0c520e680220c0ddc3f9468","published":"2021-01-17T23:44:40.182161Z"},{"version":"2.5.23","pubspec":{"name":"swiss_knife","description":"Dart Useful Tools - collections, math, date, uri, json, events, resources, regexp, etc...","version":"2.5.23","homepage":"https://github.com/gmpassos/swiss_knife","environment":{"sdk":">=2.6.0 <3.0.0"},"dependencies":{"intl":"^0.16.1","resource_portable":"^2.1.8"},"dev_dependencies":{"pedantic":"^1.9.2","test":"^1.15.4","test_coverage":"^0.4.3"}},"archive_url":"https://pub.dev/api/archives/swiss_knife-2.5.23.tar.gz","archive_sha256":"53d40e084f7e44bbda8701a5805b8d9bad4107fbe2b3c2c010788b1b357bcc1d","published":"2021-01-18T07:11:26.921592Z"},{"version":"2.5.24","pubspec":{"name":"swiss_knife","description":"Dart Useful Tools - collections, math, date, uri, json, events, resources, regexp, etc...","version":"2.5.24","homepage":"https://github.com/gmpassos/swiss_knife","environment":{"sdk":">=2.6.0 <3.0.0"},"dependencies":{"intl":"^0.16.1","resource_portable":"^2.1.8"},"dev_dependencies":{"pedantic":"^1.9.2","test":"^1.15.4","test_coverage":"^0.4.3"}},"archive_url":"https://pub.dev/api/archives/swiss_knife-2.5.24.tar.gz","archive_sha256":"833b87fb6e5312328c47b7eed229bb999c3256f5b856f75c7d199370c8219a99","published":"2021-01-19T08:46:30.967195Z"},{"version":"2.5.25","pubspec":{"name":"swiss_knife","description":"Dart Useful Tools - collections, math, date, uri, json, events, resources, regexp, etc...","version":"2.5.25","homepage":"https://github.com/gmpassos/swiss_knife","environment":{"sdk":">=2.6.0 <3.0.0"},"dependencies":{"intl":"^0.16.1","resource_portable":"^2.1.8"},"dev_dependencies":{"pedantic":"^1.9.2","test":"^1.15.4","test_coverage":"^0.4.3"}},"archive_url":"https://pub.dev/api/archives/swiss_knife-2.5.25.tar.gz","archive_sha256":"52493b0b6a10d6f367ca212e59e22058855b23d5389590fd600ed6d6109611b3","published":"2021-01-28T08:26:09.736595Z"},{"version":"2.5.26","pubspec":{"name":"swiss_knife","description":"Dart Useful Tools - collections, math, date, uri, json, events, resources, regexp, etc...","version":"2.5.26","homepage":"https://github.com/gmpassos/swiss_knife","environment":{"sdk":">=2.6.0 <3.0.0"},"dependencies":{"intl":"^0.16.1","resource_portable":"^2.1.8"},"dev_dependencies":{"pedantic":"^1.9.2","test":"^1.15.4","test_coverage":"^0.4.3"}},"archive_url":"https://pub.dev/api/archives/swiss_knife-2.5.26.tar.gz","archive_sha256":"b54fc0a094ad38ef37251499686f5f28d5953bb9d55d23d28aa83f2047eeba27","published":"2021-03-04T02:02:16.566469Z"},{"version":"3.0.0","pubspec":{"name":"swiss_knife","description":"Dart Useful Tools - collections, math, date, uri, json, events, resources, regexp, etc...","version":"3.0.0","homepage":"https://github.com/gmpassos/swiss_knife","environment":{"sdk":">=2.12.0 <3.0.0"},"dependencies":{"intl":"^0.17.0","resource_portable":"^3.0.0","collection":"^1.15.0"},"dev_dependencies":{"pedantic":"^1.11.0","test":"^1.16.5"}},"archive_url":"https://pub.dev/api/archives/swiss_knife-3.0.0.tar.gz","archive_sha256":"b985bd5b1ca419985b7d445cfca046b1df2f51c2557c63066da8fee981494902","published":"2021-03-07T09:01:28.516357Z"},{"version":"3.0.1","pubspec":{"name":"swiss_knife","description":"Dart Useful Tools - collections, math, date, uri, json, events, resources, regexp, etc...","version":"3.0.1","homepage":"https://github.com/gmpassos/swiss_knife","environment":{"sdk":">=2.12.0 <3.0.0"},"dependencies":{"intl":"^0.17.0","resource_portable":"^3.0.0","collection":"^1.15.0"},"dev_dependencies":{"pedantic":"^1.11.0","test":"^1.16.5"}},"archive_url":"https://pub.dev/api/archives/swiss_knife-3.0.1.tar.gz","archive_sha256":"6fc4f0260cbd76d00c1e252c797ee1fd6b2e003449ac2224332f68f4a659950e","published":"2021-03-08T03:18:53.016238Z"},{"version":"3.0.2","pubspec":{"name":"swiss_knife","description":"Dart Useful Tools - collections, math, date, uri, json, events, resources, regexp, etc...","version":"3.0.2","homepage":"https://github.com/gmpassos/swiss_knife","environment":{"sdk":">=2.12.0 <3.0.0"},"dependencies":{"intl":"^0.17.0","resource_portable":"^3.0.0","collection":"^1.15.0"},"dev_dependencies":{"pedantic":"^1.11.0","test":"^1.16.5"}},"archive_url":"https://pub.dev/api/archives/swiss_knife-3.0.2.tar.gz","archive_sha256":"0a8a1f82c2ad40c543559ba5a74bf00fef2a5e1212e63d0a0b5cedf1c4641aea","published":"2021-03-10T07:39:03.964801Z"},{"version":"3.0.3","pubspec":{"name":"swiss_knife","description":"Dart Useful Tools - collections, math, date, uri, json, events, resources, regexp, etc...","version":"3.0.3","homepage":"https://github.com/gmpassos/swiss_knife","environment":{"sdk":">=2.12.0 <3.0.0"},"dependencies":{"intl":"^0.17.0","resource_portable":"^3.0.0","collection":"^1.15.0"},"dev_dependencies":{"pedantic":"^1.11.0","test":"^1.16.5"}},"archive_url":"https://pub.dev/api/archives/swiss_knife-3.0.3.tar.gz","archive_sha256":"6dd65ea860820fbf87908dc83f0257aec8cb7445a8758b7177262fd8705f36bf","published":"2021-03-10T09:09:33.652592Z"},{"version":"3.0.4","pubspec":{"name":"swiss_knife","description":"Dart Useful Tools - collections, math, date, uri, json, events, resources, regexp, etc...","version":"3.0.4","homepage":"https://github.com/gmpassos/swiss_knife","environment":{"sdk":">=2.12.0 <3.0.0"},"dependencies":{"intl":"^0.17.0","resource_portable":"^3.0.0","collection":"^1.15.0"},"dev_dependencies":{"pedantic":"^1.11.0","test":"^1.16.7"}},"archive_url":"https://pub.dev/api/archives/swiss_knife-3.0.4.tar.gz","archive_sha256":"ba63fa6c99a023083d6b69af3b226032b031bb5e2e1a281040162397b06f4266","published":"2021-03-10T23:29:14.574395Z"},{"version":"3.0.5","pubspec":{"name":"swiss_knife","description":"Dart Useful Tools - collections, math, date, uri, json, events, resources, regexp, etc...","version":"3.0.5","homepage":"https://github.com/gmpassos/swiss_knife","environment":{"sdk":">=2.12.0 <3.0.0"},"dependencies":{"intl":"^0.17.0","resource_portable":"^3.0.0","collection":"^1.15.0"},"dev_dependencies":{"pedantic":"^1.11.0","test":"^1.16.7"}},"archive_url":"https://pub.dev/api/archives/swiss_knife-3.0.5.tar.gz","archive_sha256":"aee932e85d22a558f0c286ad02c81f23af27bf457da8c6ac1aba7d37693cc664","published":"2021-03-11T01:37:26.216831Z"},{"version":"3.0.6","pubspec":{"name":"swiss_knife","description":"Dart Useful Tools - collections, math, date, uri, json, events, resources, regexp, etc...","version":"3.0.6","homepage":"https://github.com/gmpassos/swiss_knife","environment":{"sdk":">=2.12.0 <3.0.0"},"dependencies":{"intl":"^0.17.0","resource_portable":"^3.0.0","collection":"^1.15.0"},"dev_dependencies":{"pedantic":"^1.11.0","test":"^1.16.7"}},"archive_url":"https://pub.dev/api/archives/swiss_knife-3.0.6.tar.gz","archive_sha256":"2e9c20e5c3705baa2665b532d259a7bd806be73758d782fb707f0119e786d53a","published":"2021-03-22T02:19:35.251170Z"},{"version":"3.0.7","pubspec":{"name":"swiss_knife","description":"Dart Useful Tools - collections, math, date, uri, json, events, resources, regexp, etc...","version":"3.0.7","homepage":"https://github.com/gmpassos/swiss_knife","environment":{"sdk":">=2.12.0 <3.0.0"},"dependencies":{"intl":"^0.17.0","resource_portable":"^3.0.0","collection":"^1.15.0"},"dev_dependencies":{"pedantic":"^1.11.0","test":"^1.16.7"}},"archive_url":"https://pub.dev/api/archives/swiss_knife-3.0.7.tar.gz","archive_sha256":"15d0b34274aed125dddb1ecce5f1fe3ff36e3a263d5ad35b8992433c17a63fb5","published":"2021-05-28T00:40:48.214392Z"},{"version":"3.0.8","pubspec":{"name":"swiss_knife","description":"Dart Useful Tools - collections, math, date, uri, json, events, resources, regexp, etc...","version":"3.0.8","homepage":"https://github.com/gmpassos/swiss_knife","environment":{"sdk":">=2.12.0 <3.0.0"},"dependencies":{"intl":"^0.17.0","resource_portable":"^3.0.0"},"dev_dependencies":{"pedantic":"^1.11.0","test":"^1.17.9","dependency_validator":"^3.1.0","collection":"^1.15.0","test_cov":"^1.0.1"}},"archive_url":"https://pub.dev/api/archives/swiss_knife-3.0.8.tar.gz","archive_sha256":"e1e06ce4fd8b38f89e5ffa05a39a111a2daa4172e7bf73a049fe4f8f13daeb1b","published":"2021-07-08T06:58:07.906685Z"},{"version":"3.1.0","pubspec":{"name":"swiss_knife","description":"Dart Useful Tools - collections, math, date, uri, json, events, resources, regexp, etc...","version":"3.1.0","homepage":"https://github.com/gmpassos/swiss_knife","environment":{"sdk":">=2.12.0 <3.0.0"},"dependencies":{"intl":"^0.17.0","resource_portable":"^3.0.0"},"dev_dependencies":{"lints":"^1.0.1","test":"^1.17.9","dependency_validator":"^3.1.0","collection":"^1.15.0","coverage":"^1.0.4"}},"archive_url":"https://pub.dev/api/archives/swiss_knife-3.1.0.tar.gz","archive_sha256":"3a511c0fc2e6c9787a2e9ddb0edfeb9a8f25e593e2165e41be536e2b8388eab0","published":"2022-04-26T23:17:29.467979Z"},{"version":"3.1.1","pubspec":{"name":"swiss_knife","description":"Dart Useful Tools - collections, math, date, uri, json, events, resources, regexp, etc...","version":"3.1.1","homepage":"https://github.com/gmpassos/swiss_knife","environment":{"sdk":">=2.12.0 <3.0.0"},"dependencies":{"intl":"^0.17.0","resource_portable":"^3.0.0"},"dev_dependencies":{"lints":"^1.0.1","test":"^1.17.9","dependency_validator":"^3.1.0","collection":"^1.15.0","coverage":"^1.0.4"}},"archive_url":"https://pub.dev/api/archives/swiss_knife-3.1.1.tar.gz","archive_sha256":"216606f39873569a74498509a2fb140c175b300afb6b628d6cbc7ec937378c46","published":"2022-04-26T23:43:33.080014Z"},{"version":"3.1.2","pubspec":{"name":"swiss_knife","description":"Dart Useful Tools - collections, math, date, uri, json, events, resources, regexp, etc...","version":"3.1.2","homepage":"https://github.com/gmpassos/swiss_knife","environment":{"sdk":">=2.12.0 <3.0.0"},"dependencies":{"intl":"^0.17.0","resource_portable":"^3.0.0"},"dev_dependencies":{"lints":"^1.0.1","test":"^1.17.12","dependency_validator":"^3.2.2","collection":"^1.17.0","coverage":"^1.6.1"}},"archive_url":"https://pub.dev/api/archives/swiss_knife-3.1.2.tar.gz","archive_sha256":"8baa4c6b61998b240da599ce66013accf84a7019b3a2e2f8bc469fddce071fa1","published":"2022-11-15T00:35:32.157239Z"},{"version":"3.1.3","pubspec":{"name":"swiss_knife","description":"Dart Useful Tools - collections, math, date, uri, json, events, resources, regexp, etc...","version":"3.1.3","homepage":"https://github.com/gmpassos/swiss_knife","environment":{"sdk":">=2.12.0 <3.0.0"},"dependencies":{"intl":"^0.18.0","resource_portable":"^3.0.1"},"dev_dependencies":{"lints":"^2.0.1","test":"^1.22.1","dependency_validator":"^3.2.2","collection":"^1.17.0","coverage":"^1.6.1"}},"archive_url":"https://pub.dev/api/archives/swiss_knife-3.1.3.tar.gz","archive_sha256":"fe7d3059c27da24eedf4ff87aadc2be27d5ed39bfbbcfab867bf43a58e6cf6f7","published":"2022-12-21T02:40:05.452462Z"},{"version":"3.1.4","pubspec":{"name":"swiss_knife","description":"Dart Useful Tools - collections, math, date, uri, json, events, resources, regexp, etc...","version":"3.1.4","homepage":"https://github.com/gmpassos/swiss_knife","environment":{"sdk":">=2.12.0 <3.0.0"},"dependencies":{"intl":"^0.18.0","resource_portable":"^3.0.1"},"dev_dependencies":{"lints":"^2.0.1","test":"^1.22.1","dependency_validator":"^3.2.2","collection":"^1.17.0","coverage":"^1.6.3"}},"archive_url":"https://pub.dev/api/archives/swiss_knife-3.1.4.tar.gz","archive_sha256":"b4073f90185aa2dfe4006e787da4792f7f3fc2b3eaca38edf54b09eff05fb47c","published":"2023-03-31T09:26:05.622521Z"},{"version":"3.1.5","pubspec":{"name":"swiss_knife","description":"Dart Useful Tools - collections, math, date, uri, json, events, resources, regexp, etc...","version":"3.1.5","homepage":"https://github.com/gmpassos/swiss_knife","environment":{"sdk":">=2.12.0 <3.0.0"},"dependencies":{"intl":"^0.18.0","resource_portable":"^3.0.1"},"dev_dependencies":{"lints":"^2.0.1","test":"^1.22.1","dependency_validator":"^3.2.2","collection":"^1.17.0","coverage":"^1.6.3"}},"archive_url":"https://pub.dev/api/archives/swiss_knife-3.1.5.tar.gz","archive_sha256":"3066fc2ed9a90139cf69f1733f6f9714f7a0a4e6a9d668451d5a1e371da8897b","published":"2023-04-11T00:19:10.875149Z"},{"version":"3.1.6","pubspec":{"name":"swiss_knife","description":"Dart Useful Tools - collections, math, date, uri, json, events, resources, regexp, etc...","version":"3.1.6","homepage":"https://github.com/gmpassos/swiss_knife","environment":{"sdk":">=2.18.0 <4.0.0"},"dependencies":{"intl":"^0.18.1","resource_portable":"^3.1.0"},"dev_dependencies":{"lints":"^2.0.1","test":"^1.22.1","dependency_validator":"^3.2.2","collection":"^1.17.0","coverage":"^1.6.3"}},"archive_url":"https://pub.dev/api/archives/swiss_knife-3.1.6.tar.gz","archive_sha256":"cf89dc6f698d0a9ca899fee788ee945725b080631025714d822595dad30f29a2","published":"2023-12-30T20:46:35.941222Z"},{"version":"3.2.0","pubspec":{"name":"swiss_knife","description":"Dart Useful Tools - collections, math, date, uri, json, events, resources, regexp, etc...","version":"3.2.0","homepage":"https://github.com/gmpassos/swiss_knife","environment":{"sdk":">=3.3.0 <4.0.0"},"dependencies":{"intl":"^0.19.0","resource_portable":"^3.1.0"},"dev_dependencies":{"lints":"^3.0.0","test":"^1.25.2","dependency_validator":"^3.2.3","collection":"^1.18.0","coverage":"^1.7.2"}},"archive_url":"https://pub.dev/api/archives/swiss_knife-3.2.0.tar.gz","archive_sha256":"25a2c21e89ad9a59ef7b15779c1c364710223239fae454bd84c10ba6e6c0c9de","published":"2024-02-15T18:06:21.724821Z"},{"version":"3.2.1","pubspec":{"name":"swiss_knife","description":"Dart Useful Tools - collections, math, date, uri, json, events, resources, regexp, etc...","version":"3.2.1","homepage":"https://github.com/gmpassos/swiss_knife","environment":{"sdk":">=3.3.0 <4.0.0"},"dependencies":{"intl":"^0.19.0","resource_portable":"^3.1.0"},"dev_dependencies":{"lints":"^3.0.0","test":"^1.25.8","dependency_validator":"^3.2.3","collection":"^1.18.0","coverage":"^1.9.0"}},"archive_url":"https://pub.dev/api/archives/swiss_knife-3.2.1.tar.gz","archive_sha256":"25867268e64837d27463aa806b38acf1bed0c92097d9885ec769e85aa1e818b5","published":"2024-08-09T05:33:17.505567Z"},{"version":"3.2.2","pubspec":{"name":"swiss_knife","description":"Dart Useful Tools - collections, math, date, uri, json, events, resources, regexp, etc...","version":"3.2.2","homepage":"https://github.com/gmpassos/swiss_knife","environment":{"sdk":">=3.3.0 <4.0.0"},"dependencies":{"intl":"^0.19.0","resource_portable":"^3.1.0"},"dev_dependencies":{"lints":"^3.0.0","test":"^1.25.8","dependency_validator":"^3.2.3","collection":"^1.18.0","coverage":"^1.9.2"}},"archive_url":"https://pub.dev/api/archives/swiss_knife-3.2.2.tar.gz","archive_sha256":"c0b011aab38df274c08f90ce42549aa66d744115c011e07a9bd21402d6be297d","published":"2024-09-14T08:01:15.749783Z"}],"_fetchedAt":"2024-11-30T12:02:34.263509"}